curses_colors/__init__.py
curses_colors/curses_colors.py
curses_colors-0.1.0.dist-info/METADATA
curses_colors-0.1.0.dist-info/WHEEL
curses_colors-0.1.0.dist-info/top_level.txt
curses_colors-0.1.0.dist-info/RECORD
