Metadata-Version: 2.4
Name: curses-colors
Version: 0.1.0
Summary: `curses-colors` is a Python module that provides a simple interface for managing color pairs in a terminal using the `curses` library.
Home-page: https://github.com/xlebore3o4ka/curses-colors/tree/main
Author: xlebore3o4ka
Author-email: xlebore3o4ka@gmail.com
Classifier: Programming Language :: Python :: 3
Classifier: License :: OSI Approved :: MIT License
Classifier: Operating System :: OS Independent
Requires-Python: >=3.6
Dynamic: author
Dynamic: author-email
Dynamic: classifier
Dynamic: description
Dynamic: description-content-type
Dynamic: home-page
Dynamic: requires-python
Dynamic: summary
